examples/README.md
examples/__init__.py
examples/base_settings.py
examples/callbacks.py
examples/consumer.py
examples/example_aws_settings.py
examples/example_gcp_settings.py
examples/example_redis_streams_settings.py
examples/init_gcp.py
examples/models.py
examples/publisher.py
examples/requeue_dlq.py
examples/protos/__init__.py
examples/protos/schema_pb2.py
examples/protos/schema_pb2.pyi
hedwig/__init__.py
hedwig/callback.py
hedwig/commands.py
hedwig/consumer.py
hedwig/exceptions.py
hedwig/models.py
hedwig/publisher.py
hedwig/py.typed
hedwig/utils.py
hedwig/backends/__init__.py
hedwig/backends/aws.py
hedwig/backends/base.py
hedwig/backends/exceptions.py
hedwig/backends/gcp.py
hedwig/backends/import_utils.py
hedwig/backends/redis.py
hedwig/backends/utils.py
hedwig/conf/__init__.py
hedwig/instrumentation/__init__.py
hedwig/instrumentation/compat.py
hedwig/protobuf/__init__.py
hedwig/protobuf/container_pb2.py
hedwig/protobuf/container_pb2.pyi
hedwig/protobuf/options_pb2.py
hedwig/protobuf/options_pb2.pyi
hedwig/testing/__init__.py
hedwig/testing/config.py
hedwig/testing/pytest_plugin.py
hedwig/testing/factories/__init__.py
hedwig/testing/factories/base.py
hedwig/testing/factories/jsonschema.py
hedwig/testing/factories/protobuf.py
hedwig/validators/__init__.py
hedwig/validators/base.py
hedwig/validators/jsonschema.py
hedwig/validators/jsonschema_container_schema.json
hedwig/validators/protobuf.py
authedwig-11.0.0.dist-info/LICENSE.md
authedwig-11.0.0.dist-info/METADATA
authedwig-11.0.0.dist-info/WHEEL
authedwig-11.0.0.dist-info/entry_points.txt
authedwig-11.0.0.dist-info/top_level.txt
authedwig-11.0.0.dist-info/RECORD
