Metadata-Version: 2.2
Name: authedwig
Version: 11.0.0
Summary: Hedwig Python Library
Home-page: https://github.com/cloudchacho/hedwig-python
Author: Cloudchacho
Maintainer: Aniruddha Maru
Maintainer-email: maru@aniruddhamaru.com
License: Apache Software License (Apache License 2.0)
Keywords: python authedwig hedwig
Classifier: Natural Language :: English
Classifier: Development Status :: 5 - Production/Stable
Classifier: Intended Audience :: Developers
Classifier: Intended Audience :: System Administrators
Classifier: Topic :: Software Development :: Libraries :: Python Modules
Classifier: Programming Language :: Python
Classifier: Programming Language :: Python :: 3.9
Classifier: Programming Language :: Python :: 3.10
Classifier: Programming Language :: Python :: 3.11
Classifier: Programming Language :: Python :: 3.12
Classifier: Programming Language :: Python :: 3.13
Classifier: License :: OSI Approved :: Apache Software License
Requires-Python: >=3.9
License-File: LICENSE.md
Requires-Dist: funcy
Requires-Dist: dataclasses; python_version < "3.7"
Provides-Extra: aws
Requires-Dist: boto3; extra == "aws"
Requires-Dist: retrying; extra == "aws"
Provides-Extra: gcp
Requires-Dist: google-cloud-pubsub>=2.0.0; extra == "gcp"
Requires-Dist: grpcio-status; extra == "gcp"
Provides-Extra: dev
Requires-Dist: boto3-stubs[sns,sqs]; extra == "dev"
Requires-Dist: docutils<0.18; python_version < "3.8" and extra == "dev"
Requires-Dist: flake8; extra == "dev"
Requires-Dist: jinja2<3.1; (python_version >= "3.7" and python_version < "3.8") and extra == "dev"
Requires-Dist: mypy-protobuf; extra == "dev"
Requires-Dist: pip-tools; extra == "dev"
Requires-Dist: protobuf~=6.0; extra == "dev"
Requires-Dist: Sphinx==3.2.1; python_version < "3.8" and extra == "dev"
Requires-Dist: Sphinx>3; python_version >= "3.8" and extra == "dev"
Requires-Dist: sphinx-autodoc-typehints<1.13.0; python_version < "3.8" and extra == "dev"
Requires-Dist: sphinx-autodoc-typehints; python_version >= "3.8" and extra == "dev"
Requires-Dist: types-dataclasses; extra == "dev"
Requires-Dist: types-protobuf<3.20.0; extra == "dev"
Requires-Dist: wheel; extra == "dev"
Provides-Extra: jsonschema
Requires-Dist: jsonpointer; extra == "jsonschema"
Requires-Dist: jsonschema; extra == "jsonschema"
Provides-Extra: protobuf
Requires-Dist: protobuf~=6.0; extra == "protobuf"
Provides-Extra: redis
Requires-Dist: redis; extra == "redis"
Provides-Extra: test
Requires-Dist: black; extra == "test"
Requires-Dist: coverage; extra == "test"
Requires-Dist: coveralls; extra == "test"
Requires-Dist: factory-boy; extra == "test"
Requires-Dist: flake8; extra == "test"
Requires-Dist: freezegun; extra == "test"
Requires-Dist: ipdb; extra == "test"
Requires-Dist: moto[sns,sqs]; extra == "test"
Requires-Dist: mypy; extra == "test"
Requires-Dist: opentelemetry-sdk; extra == "test"
Requires-Dist: protobuf; extra == "test"
Requires-Dist: pytest; extra == "test"
Requires-Dist: pytest-cov; extra == "test"
Requires-Dist: pytest-env; extra == "test"
Requires-Dist: structlog; extra == "test"
Provides-Extra: publish
Requires-Dist: bumpversion; extra == "publish"
Requires-Dist: twine; extra == "publish"
Provides-Extra: opentelemetry
Requires-Dist: opentelemetry-api; extra == "opentelemetry"
Dynamic: author
Dynamic: classifier
Dynamic: description
Dynamic: home-page
Dynamic: keywords
Dynamic: license
Dynamic: maintainer
Dynamic: maintainer-email
Dynamic: provides-extra
Dynamic: requires-dist
Dynamic: requires-python
Dynamic: summary
